[
    {
        "bvid": "BV1Xm4y197Bo",
        "title": "成 龙 劝 学",
        "mid": 375375,
        "author": "伊丽莎白鼠",
        "play": 5271699,
        "danmu": 10048,
        "comment": 7252,
        "like": 573934,
        "coin": 228212,
        "collect": 118153
    },
    {
        "bvid": "BV1FF411J71Q",
        "title": "耗时五个月！高中生自制翻拍的《艾斯奥特曼》终于来了！",
        "mid": 432938640,
        "author": "阿呆同学啊",
        "play": 2954437,
        "danmu": 22099,
        "comment": 9509,
        "like": 324648,
        "coin": 264298,
        "collect": 76986
    },
    {
        "bvid": "BV1iP4y1F7Kq",
        "title": "全员崩溃！从业至今，还从未见识过这种场面…",
        "mid": 1590082082,
        "author": "马俐管家",
        "play": 7440369,
        "danmu": 44057,
        "comment": 23474,
        "like": 477965,
        "coin": 167078,
        "collect": 53467
    },
    {
        "bvid": "BV1Uq4y1t7ME",
        "title": "攒足了10个超赞的家庭小料理，学会了做给家人吃，你一定会回来谢我 ….炭烤牛排、孜然羊排、真蒜味面包、鲍耗双拼、牛排盖饭、芝士土豆泥、蒜辣意面、祖传饼干、鸡芝圈",
        "mid": 86138838,
        "author": "阿男的食谱",
        "play": 7023382,
        "danmu": 2806,
        "comment": 2922,
        "like": 483144,
        "coin": 40321,
        "collect": 250666
    },
    {
        "bvid": "BV1k34y1C7CL",
        "title": "【老番茄】大傻子福尔摩斯(第二集)",
        "mid": 546195,
        "author": "老番茄",
        "play": 2760614,
        "danmu": 16437,
        "comment": 5258,
        "like": 367242,
        "coin": 193190,
        "collect": 78579
    },
    {
        "bvid": "BV19r4y167pL",
        "title": "历时40天、200小时 我终于一命通关了造梦西游3！",
        "mid": 344488725,
        "author": "易凌叔",
        "play": 3360343,
        "danmu": 13775,
        "comment": 3845,
        "like": 400284,
        "coin": 413136,
        "collect": 106549
    },
    {
        "bvid": "BV1W3411L7LS",
        "title": "劫匪：找到你的把柄啦！！哈哈哈哈哈哈！！！！！",
        "mid": 5294454,
        "author": "逗比的雀巢",
        "play": 4608083,
        "danmu": 7694,
        "comment": 5893,
        "like": 492143,
        "coin": 135538,
        "collect": 57982
    },
    {
        "bvid": "BV1Br4y167bX",
        "title": "香菱怒斥钟离吃饭不给钱",
        "mid": 32618090,
        "author": "托比昂的护甲包",
        "play": 3028693,
        "danmu": 2559,
        "comment": 3696,
        "like": 295326,
        "coin": 128196,
        "collect": 117874
    },
    {
        "bvid": "BV1vL411K7UN",
        "title": "【STN快报第六季21】为了拯救工作室！白金竟说自己可以出来卖！",
        "mid": 7349,
        "author": "STN工作室",
        "play": 1565998,
        "danmu": 19347,
        "comment": 2960,
        "like": 186672,
        "coin": 214641,
        "collect": 51928
    },
    {
        "bvid": "BV1nm4y1o7Am",
        "title": "30秒讲完《哈利波特》",
        "mid": 1238329219,
        "author": "觅2",
        "play": 1535358,
        "danmu": 448,
        "comment": 988,
        "like": 119143,
        "coin": 6106,
        "collect": 20289
    },
    {
        "bvid": "BV1fm4y1d7Tg",
        "title": "【时代少年团】宋亚轩刘耀文《一起等雨停》",
        "mid": 3670216,
        "author": "TF家族",
        "play": 2193613,
        "danmu": 148007,
        "comment": 83615,
        "like": 242021,
        "coin": 137555,
        "collect": 115890
    },
    {
        "bvid": "BV1qa411C7ni",
        "title": "带英水兵如何讨薪？【硬核狠人27】",
        "mid": 23947287,
        "author": "小约翰可汗",
        "play": 3004065,
        "danmu": 26578,
        "comment": 9294,
        "like": 264667,
        "coin": 162592,
        "collect": 40729
    },
    {
        "bvid": "BV1Hr4y1r79s",
        "title": "来来来！我赌你顶不住这锅《 羊 的 诱 惑 》",
        "mid": 18202105,
        "author": "绵羊料理",
        "play": 2869145,
        "danmu": 9683,
        "comment": 3006,
        "like": 280284,
        "coin": 121306,
        "collect": 24354
    },
    {
        "bvid": "BV1xr4y1r7Vn",
        "title": "可怜的水史莱姆",
        "mid": 503400701,
        "author": "刘琥动画",
        "play": 1549930,
        "danmu": 489,
        "comment": 4905,
        "like": 209898,
        "coin": 29111,
        "collect": 47999
    },
    {
        "bvid": "BV1M44y1n7Db",
        "title": "这个up又疯了，他算出了海绵宝宝家里有多大，附带详细户型图。。。",
        "mid": 13279707,
        "author": "最上川下山",
        "play": 5332613,
        "danmu": 4858,
        "comment": 3734,
        "like": 393458,
        "coin": 144438,
        "collect": 81209
    },
    {
        "bvid": "BV1CY411L7hN",
        "title": "记住八个规律，想字丑都难",
        "mid": 479551750,
        "author": "墨竹手写",
        "play": 4104895,
        "danmu": 1305,
        "comment": 3431,
        "like": 305192,
        "coin": 77030,
        "collect": 366526
    },
    {
        "bvid": "BV1mu411X7TB",
        "title": "【才浅手工】猛男还原魔法少女水晶魔法棒，什么是魔法？看完你就知道了！",
        "mid": 2200736,
        "author": "才疏学浅的才浅",
        "play": 2655499,
        "danmu": 12654,
        "comment": 3990,
        "like": 305958,
        "coin": 126694,
        "collect": 43069
    },
    {
        "bvid": "BV1iq4y1t7hb",
        "title": "终于找到2008年夏天那个叫“群星”的歌手了",
        "mid": 1131457022,
        "author": "人民日报",
        "play": 3775946,
        "danmu": 8954,
        "comment": 5414,
        "like": 331604,
        "coin": 111621,
        "collect": 67790
    },
    {
        "bvid": "BV1AY41157yH",
        "title": "作为理发师，这是今年剪的最爽的一颗头。",
        "mid": 1869712375,
        "author": "山城小栗旬的理发日记",
        "play": 3335073,
        "danmu": 18270,
        "comment": 7508,
        "like": 251960,
        "coin": 81843,
        "collect": 16662
    },
    {
        "bvid": "BV1pZ4y1k7oD",
        "title": "【钉宫理惠】B站的大家别催了，这就来骂啦！",
        "mid": 1254786108,
        "author": "钉宫理惠",
        "play": 2156861,
        "danmu": 11523,
        "comment": 44686,
        "like": 203512,
        "coin": 97291,
        "collect": 30471
    },
    {
        "bvid": "BV1QL411K7rz",
        "title": "【妈见打】我在卧室墙上画了EVA！",
        "mid": 34070103,
        "author": "师梦徽瑜",
        "play": 474373,
        "danmu": 437,
        "comment": 1434,
        "like": 65542,
        "coin": 6641,
        "collect": 19261
    },
    {
        "bvid": "BV1u34y1y7tY",
        "title": "我和高中时喜欢的女孩子在一起了",
        "mid": 12842284,
        "author": "气球屋w",
        "play": 3004901,
        "danmu": 15935,
        "comment": 13222,
        "like": 173509,
        "coin": 73471,
        "collect": 30801
    },
    {
        "bvid": "BV1VY41157AJ",
        "title": "它没钱没流量，但给内娱好好打了个样！",
        "mid": 5870268,
        "author": "三代鹿人",
        "play": 2651771,
        "danmu": 8621,
        "comment": 4992,
        "like": 278659,
        "coin": 79702,
        "collect": 29305
    },
    {
        "bvid": "BV1XT4y1D7Nc",
        "title": "B站小伙伴们的力量借我一用！石黑英雄正式入驻B站啦！",
        "mid": 1978885142,
        "author": "石黑英雄",
        "play": 1305195,
        "danmu": 6815,
        "comment": 9351,
        "like": 147181,
        "coin": 71073,
        "collect": 26589
    },
    {
        "bvid": "BV1TS4y1F7Pe",
        "title": "全网首吃疣背蜘蛛蟹，全程惊喜连连，差点hold不住",
        "mid": 476704454,
        "author": "小文哥吃吃吃",
        "play": 2340143,
        "danmu": 9173,
        "comment": 1891,
        "like": 259917,
        "coin": 63478,
        "collect": 12236
    },
    {
        "bvid": "BV1xu411X71m",
        "title": "【方舟沙雕动画】夕宝你又在喷墨哦，来吃个饭吧",
        "mid": 41039728,
        "author": "博丽x海苔",
        "play": 1020082,
        "danmu": 1297,
        "comment": 1546,
        "like": 154559,
        "coin": 75116,
        "collect": 79033
    },
    {
        "bvid": "BV1KP4y1A7AY",
        "title": "第一次见面就互看……太羞耻啦！【梦幻联动01夏波波-传奇大锅台】",
        "mid": 452606628,
        "author": "王师傅和小毛毛",
        "play": 1250976,
        "danmu": 10700,
        "comment": 2449,
        "like": 220378,
        "coin": 81950,
        "collect": 16266
    },
    {
        "bvid": "BV1ca411C7oW",
        "title": "原神躲猫猫小动画_(:з」∠)_",
        "mid": 4637682,
        "author": "绘之音",
        "play": 852317,
        "danmu": 706,
        "comment": 1751,
        "like": 128110,
        "coin": 41559,
        "collect": 43044
    },
    {
        "bvid": "BV18T4y1D7dF",
        "title": "一刀下去，全面实现冰墩墩自由！",
        "mid": 35781763,
        "author": "七分甜的秋刀鱼",
        "play": 3863884,
        "danmu": 15275,
        "comment": 3801,
        "like": 259655,
        "coin": 99391,
        "collect": 44814
    },
    {
        "bvid": "BV1Z44y1J7h7",
        "title": "《STAY》完整版来啦！真·经典重现！！！",
        "mid": 477676711,
        "author": "田一名sir",
        "play": 2474859,
        "danmu": 7057,
        "comment": 5118,
        "like": 242388,
        "coin": 99597,
        "collect": 31709
    },
    {
        "bvid": "BV1oS4y1r76H",
        "title": "穿搭配色的秘密，我给每个人都找到了！【晓观】",
        "mid": 207261582,
        "author": "晓观队长",
        "play": 2290352,
        "danmu": 4090,
        "comment": 3242,
        "like": 252061,
        "coin": 178917,
        "collect": 128946
    },
    {
        "bvid": "BV1yT4y1D7mh",
        "title": "小姐姐说想要坐在熊身上 熊：来呀来呀 【街头恶作剧挑战66】",
        "mid": 333020125,
        "author": "野生大肥扬",
        "play": 6195367,
        "danmu": 4536,
        "comment": 2875,
        "like": 388610,
        "coin": 19333,
        "collect": 58227
    },
    {
        "bvid": "BV1gb4y1t7WG",
        "title": "《鬼灭之刃·无限游郭篇》 飞碟社都不敢这么编！！",
        "mid": 41149747,
        "author": "怪兽电台MonsterBlog",
        "play": 911851,
        "danmu": 1670,
        "comment": 1508,
        "like": 73096,
        "coin": 60239,
        "collect": 31092
    },
    {
        "bvid": "BV1vY411V7rn",
        "title": "为了给小猫咪减肥，我把我爸的车开烂了...",
        "mid": 518990456,
        "author": "詹詹家的猫meow",
        "play": 2185007,
        "danmu": 2494,
        "comment": 1179,
        "like": 285705,
        "coin": 27104,
        "collect": 11067
    },
    {
        "bvid": "BV14u411X7H7",
        "title": "【医学博士】祸从口入，一口吃掉6000只寄生虫？I 人类最容易感染的三种寄生虫",
        "mid": 7788379,
        "author": "兔叭咯",
        "play": 3364155,
        "danmu": 9460,
        "comment": 3639,
        "like": 229064,
        "coin": 66534,
        "collect": 24235
    },
    {
        "bvid": "BV1Rm4y1d7SJ",
        "title": "三年的雪，人们见到都疯了...",
        "mid": 1577804,
        "author": "某幻君",
        "play": 1365455,
        "danmu": 7176,
        "comment": 2670,
        "like": 146131,
        "coin": 49827,
        "collect": 27141
    },
    {
        "bvid": "BV1Ya411C79x",
        "title": "【原神】【原创动画】生草眼镜",
        "mid": 94792232,
        "author": "Far远东",
        "play": 1350595,
        "danmu": 2986,
        "comment": 1861,
        "like": 197679,
        "coin": 99134,
        "collect": 86566
    },
    {
        "bvid": "BV1hT4y1Q7SE",
        "title": "女朋友睡醒后竟然变成了男人【阅片无数Ⅱ 37】",
        "mid": 14110780,
        "author": "凉风Kaze",
        "play": 1545703,
        "danmu": 11625,
        "comment": 2727,
        "like": 175664,
        "coin": 25121,
        "collect": 10330
    },
    {
        "bvid": "BV1LY411G71N",
        "title": "印度小鱼啃脚",
        "mid": 533459953,
        "author": "刘庸干净又卫生",
        "play": 2515813,
        "danmu": 12567,
        "comment": 6126,
        "like": 204363,
        "coin": 13521,
        "collect": 5634
    },
    {
        "bvid": "BV1TY41157h1",
        "title": "《原神》2022宣传视频-「来自群星」愿前路永无止境-《Constellation》",
        "mid": 282960675,
        "author": "-阿洋Yoko-",
        "play": 1218350,
        "danmu": 2930,
        "comment": 3021,
        "like": 212512,
        "coin": 115169,
        "collect": 94794
    },
    {
        "bvid": "BV1kF411E7X2",
        "title": "朋友们，牛皮你们吃过吗？今天分享三种牛皮的做法给大家看看",
        "mid": 2017576198,
        "author": "唐小米婆婆",
        "play": 4013793,
        "danmu": 8490,
        "comment": 5473,
        "like": 331814,
        "coin": 25206,
        "collect": 38475
    },
    {
        "bvid": "BV18P4y1F7zx",
        "title": "没节操被打，到底是猫德的沦丧，还是道德的缺失！",
        "mid": 508416316,
        "author": "本喵叫兔兔",
        "play": 2002552,
        "danmu": 1038,
        "comment": 2005,
        "like": 234417,
        "coin": 10220,
        "collect": 11788
    },
    {
        "bvid": "BV1Zb4y147oV",
        "title": "离谱！假装在女友面前叹气流眼泪…她竟然不停亲我？",
        "mid": 285571498,
        "author": "盖里老哥",
        "play": 1412525,
        "danmu": 7455,
        "comment": 7325,
        "like": 145679,
        "coin": 92399,
        "collect": 20060
    },
    {
        "bvid": "BV1BZ4y1k79J",
        "title": "美国嚷嚷半天“狼来了”，普京：来就来【轩讲】",
        "mid": 10330740,
        "author": "观察者网",
        "play": 1852668,
        "danmu": 7922,
        "comment": 3351,
        "like": 100015,
        "coin": 14551,
        "collect": 9722
    },
    {
        "bvid": "BV1ub4y1t7ec",
        "title": "我有帽子猫啦！",
        "mid": 18374719,
        "author": "红糖打年糕",
        "play": 1681313,
        "danmu": 2439,
        "comment": 3956,
        "like": 163337,
        "coin": 43544,
        "collect": 50543
    },
    {
        "bvid": "BV1nZ4y1k741",
        "title": "俄罗斯大部分艺术家都不富有",
        "mid": 677680777,
        "author": "你的俄罗斯好朋友诺娜",
        "play": 4973060,
        "danmu": 1254,
        "comment": 3657,
        "like": 603447,
        "coin": 22539,
        "collect": 67217
    },
    {
        "bvid": "BV1Jm4y1o7Ef",
        "title": "周 杰 伦",
        "mid": 101376123,
        "author": "秋名山上的486",
        "play": 1772492,
        "danmu": 2257,
        "comment": 1939,
        "like": 151061,
        "coin": 64467,
        "collect": 34914
    },
    {
        "bvid": "BV1ur4y1r7M7",
        "title": "鉴定网络热门艺术（17）",
        "mid": 330663625,
        "author": "站不起来的蒙蒙",
        "play": 3589422,
        "danmu": 2933,
        "comment": 1680,
        "like": 277032,
        "coin": 15776,
        "collect": 20937
    }
]